stringsight/__init__.py
stringsight/__main__.py
stringsight/api.py
stringsight/celery_app.py
stringsight/cli.py
stringsight/config.py
stringsight/constants.py
stringsight/database.py
stringsight/logging_config.py
stringsight/pipeline.py
stringsight/prompt_generation.py
stringsight/public.py
stringsight/schemas.py
stringsight/_public/__init__.py
stringsight/_public/async_api.py
stringsight/_public/convenience.py
stringsight/_public/helpers.py
stringsight/_public/label_api.py
stringsight/_public/metrics_only.py
stringsight/_public/pipeline_builders.py
stringsight/_public/sync_api.py
stringsight/clusterers/__init__.py
stringsight/clusterers/base.py
stringsight/clusterers/clustering_utils.py
stringsight/clusterers/config.py
stringsight/clusterers/dummy_clusterer.py
stringsight/clusterers/hdbscan.py
stringsight/clusterers/hierarchical_clustering.py
stringsight/core/__init__.py
stringsight/core/api_cache.py
stringsight/core/api_helpers.py
stringsight/core/caching.py
stringsight/core/data_objects.py
stringsight/core/llm_utils.py
stringsight/core/mixins.py
stringsight/core/preprocessing.py
stringsight/core/stage.py
stringsight/db_models/__init__.py
stringsight/db_models/job.py
stringsight/db_models/user.py
stringsight/extractors/__init__.py
stringsight/extractors/batch.py
stringsight/extractors/conv_to_str.py
stringsight/extractors/fixed_axes_labeler.py
stringsight/extractors/inp_to_conv.py
stringsight/extractors/openai.py
stringsight/formatters/__init__.py
stringsight/formatters/traces.py
stringsight/frontend/node_modules/flatted/python/flatted.py
stringsight/frontend/node_modules/katex/src/fonts/generate_fonts.py
stringsight/frontend/node_modules/katex/src/metrics/extract_tfms.py
stringsight/frontend/node_modules/katex/src/metrics/extract_ttfs.py
stringsight/frontend/node_modules/katex/src/metrics/format_json.py
stringsight/frontend/node_modules/katex/src/metrics/parse_tfm.py
stringsight/frontend/node_modules/plotly.js/.circleci/download_google_fonts.py
stringsight-0.3.7.dist-info/licenses/LICENSE
stringsight-0.3.7.dist-info/METADATA
stringsight-0.3.7.dist-info/WHEEL
stringsight-0.3.7.dist-info/entry_points.txt
stringsight-0.3.7.dist-info/top_level.txt
stringsight-0.3.7.dist-info/RECORD
