Metadata-Version: 2.4
Name: stringsight
Version: 0.3.7
Summary: Explain Large Language Model Behavior Patterns
Author-email: Lisa Dunlap <lisabdunlap@berkeley.edu>
Project-URL: Homepage, https://github.com/lisadunlap/stringsight
Project-URL: Repository, https://github.com/lisadunlap/stringsight
Project-URL: Documentation, https://github.com/lisadunlap/stringsight/blob/main/README.md
Project-URL: Bug Tracker, https://github.com/lisadunlap/stringsight/issues
Classifier: Development Status :: 3 - Alpha
Classifier: Intended Audience :: Developers
Classifier: Intended Audience :: Science/Research
Classifier: Topic :: Scientific/Engineering :: Artificial Intelligence
Classifier: License :: OSI Approved :: MIT License
Classifier: Programming Language :: Python :: 3
Classifier: Programming Language :: Python :: 3.10
Classifier: Programming Language :: Python :: 3.11
Classifier: Programming Language :: Python :: 3.12
Requires-Python: >=3.10
License-File: LICENSE
Requires-Dist: pandas>=2.0.0
Requires-Dist: numpy<2.0,>=1.19.3
Requires-Dist: scipy>=1.9.0
Requires-Dist: scikit-learn<1.6.0,>=1.3.0
Requires-Dist: tqdm>=4.65.0
Requires-Dist: pydantic>=2.0.0
Requires-Dist: pydantic-settings>=2.1.0
Requires-Dist: litellm>=1.0.0
Requires-Dist: hdbscan>=0.8.40
Requires-Dist: openai>=1.0.0
Requires-Dist: plotly>=5.15.0
Requires-Dist: fastapi>=0.100.0
Requires-Dist: uvicorn>=0.20.0
Requires-Dist: h11>=0.14.0
Requires-Dist: python-multipart>=0.0.6
Requires-Dist: omegaconf>=2.3.0
Requires-Dist: lmdb>=1.4.1
Requires-Dist: orjson>=3.9.0
Requires-Dist: xxhash>=3.4.0
Requires-Dist: nest-asyncio>=1.5.0
Requires-Dist: sqlalchemy>=2.0.0
Requires-Dist: alembic>=1.13.0
Requires-Dist: psycopg2-binary>=2.9.0
Requires-Dist: redis>=5.0.0
Requires-Dist: celery[redis]>=5.3.0
Provides-Extra: wandb
Requires-Dist: wandb>=0.15.0; extra == "wandb"
Provides-Extra: dev
Requires-Dist: pytest>=6.0; extra == "dev"
Requires-Dist: pytest-cov>=2.0; extra == "dev"
Requires-Dist: black>=21.0; extra == "dev"
Requires-Dist: mypy>=0.900; extra == "dev"
Provides-Extra: local-embeddings
Requires-Dist: sentence-transformers>=5.1.0; extra == "local-embeddings"
Provides-Extra: ml
Requires-Dist: torch>=2.0.0; extra == "ml"
Requires-Dist: transformers>=4.56.1; extra == "ml"
Requires-Dist: datasets>=2.14.0; extra == "ml"
Requires-Dist: vllm>=0.3.0; extra == "ml"
Provides-Extra: full
Requires-Dist: torch>=2.0.0; extra == "full"
Requires-Dist: transformers>=4.56.1; extra == "full"
Requires-Dist: datasets>=2.14.0; extra == "full"
Requires-Dist: vllm>=0.3.0; extra == "full"
Requires-Dist: jupyter>=1.0.0; extra == "full"
Requires-Dist: ipykernel>=6.0.0; extra == "full"
Requires-Dist: sentence-transformers>=5.1.0; extra == "full"
Requires-Dist: wandb>=0.15.0; extra == "full"
Dynamic: license-file
